single_version/__init__.py
single_version/ver.py
single_version-1.5.1.dist-info/LICENSE
single_version-1.5.1.dist-info/WHEEL
single_version-1.5.1.dist-info/METADATA
single_version-1.5.1.dist-info/RECORD
